campubtestpip/__init__.py
campubtestpip/__main__.py
campubtestpip/src/__init__.py
campubtestpip/src/utils.py
campubtestpip-0.0.8.dist-info/LICENSE
campubtestpip-0.0.8.dist-info/METADATA
campubtestpip-0.0.8.dist-info/WHEEL
campubtestpip-0.0.8.dist-info/entry_points.txt
campubtestpip-0.0.8.dist-info/top_level.txt
campubtestpip-0.0.8.dist-info/RECORD
